{
    "login": "TheAlgorithms",
    "id": 20487725,
    "node_id": "MDEyOk9yZ2FuaXphdGlvbjIwNDg3NzI1",
    "avatar_url": "https://avatars.githubusercontent.com/u/20487725?v=4",
    "gravatar_id": "",
    "url": "https://api.github.com/users/TheAlgorithms",
    "html_url": "https://github.com/TheAlgorithms",
    "followers_url": "https://api.github.com/users/TheAlgorithms/followers",
    "following_url": "https://api.github.com/users/TheAlgorithms/following{/other_user}",
    "gists_url": "https://api.github.com/users/TheAlgorithms/gists{/gist_id}",
    "starred_url": "https://api.github.com/users/TheAlgorithms/starred{/owner}{/repo}",
    "subscriptions_url": "https://api.github.com/users/TheAlgorithms/subscriptions",
    "organizations_url": "https://api.github.com/users/TheAlgorithms/orgs",
    "repos_url": "https://api.github.com/users/TheAlgorithms/repos",
    "events_url": "https://api.github.com/users/TheAlgorithms/events{/privacy}",
    "received_events_url": "https://api.github.com/users/TheAlgorithms/received_events",
    "type": "Organization",
    "site_admin": false,
    "name": "The Algorithms",
    "company": null,
    "blog": "https://the-algorithms.com/",
    "location": "India",
    "email": "hello@the-algorithms.com",
    "hireable": null,
    "bio": "Open Source resource for learning Data Structures & Algorithms and their implementation in any Programming Language",
    "twitter_username": "the_algorithms",
    "public_repos": 34,
    "public_gists": 0,
    "followers": 0,
    "following": 0,
    "created_at": "2016-07-16T08:17:02Z",
    "updated_at": "2021-05-08T06:44:32Z"
}